plot_dufte/__init__.py
plot_dufte/config_theme.py
plot_dufte/plots/__init__.py
plot_dufte/plots/dot_dash_plot.py
plot_dufte/plots/layered_focus.py
plot_dufte/plots/range_frame.py
plot_dufte/plots/slopegraph.py
plot_dufte/plots/small_multiples.py
plot_dufte/plots/sparklines.py
plot_dufte/plots/time_series.py
plot_dufte-0.1.5.dist-info/METADATA
plot_dufte-0.1.5.dist-info/WHEEL
plot_dufte-0.1.5.dist-info/entry_points.txt
plot_dufte-0.1.5.dist-info/licenses/LICENSE
plot_dufte-0.1.5.dist-info/RECORD
