Metadata-Version: 2.4
Name: plot-dufte
Version: 0.1.5
Summary: Dufte - Ein Python-Paket für Tufte-Style Plots
License: MIT
License-File: LICENSE
Requires-Python: >=3.10,<4.0
Classifier: License :: OSI Approved :: MIT License
Classifier: Programming Language :: Python :: 3
Classifier: Programming Language :: Python :: 3.10
Classifier: Programming Language :: Python :: 3.11
Classifier: Programming Language :: Python :: 3.12
Classifier: Programming Language :: Python :: 3.13
Classifier: Programming Language :: Python :: 3.14
Requires-Dist: plotnine (>=0.12.4)
Project-URL: Documentation, https://Saplinging.github.io/plot-dufte/
Project-URL: Repository, https://github.com/Saplinging/dufte
